hb_v5_basic_func/__init__.py
hb_v5_basic_func/index.py
hb_v5_basic_func/setup.py
hb_v5_basic_func/pyarmor_runtime_000000/__init__.py
hb_v5_basic_func/pyarmor_runtime_000000/pyarmor_runtime.so
hb_v5_basic_func-1.0.0.dist-info/METADATA
hb_v5_basic_func-1.0.0.dist-info/WHEEL
hb_v5_basic_func-1.0.0.dist-info/top_level.txt
hb_v5_basic_func-1.0.0.dist-info/RECORD
