Metadata-Version: 2.4
Name: hb_v5_basic_func
Version: 1.0.0
Summary: Basic function package with Pyarmor protection
Home-page: https://github.com/unknown/hb_v5_basic_func
Author: Unknown
Author-email: unknown@example.com
Project-URL: Bug Reports, https://github.com/unknown/basic_func/issues
Project-URL: Source, https://github.com/unknown/basic_func
Classifier: Development Status :: 3 - Alpha
Classifier: Intended Audience :: Developers
Classifier: License :: OSI Approved :: MIT License
Classifier: Operating System :: OS Independent
Classifier: Programming Language :: Python :: 3
Classifier: Programming Language :: Python :: 3.6
Classifier: Programming Language :: Python :: 3.7
Classifier: Programming Language :: Python :: 3.8
Classifier: Programming Language :: Python :: 3.9
Classifier: Programming Language :: Python :: 3.10
Classifier: Programming Language :: Python :: 3.11
Requires-Python: >=3.6
Dynamic: author
Dynamic: author-email
Dynamic: classifier
Dynamic: description-content-type
Dynamic: home-page
Dynamic: requires-python
Dynamic: summary
